abinator/__init__.py
abinator/abi_logic.py
abinator/events.py
abinator/inputs.py
abinator/state_mutability.py
abinator/types.py
abinator/common_abis/__init__.py
abinator/common_abis/erc20.py
abinator/common_abis/weth9.py
abinator-0.0.6.dist-info/METADATA
abinator-0.0.6.dist-info/WHEEL
abinator-0.0.6.dist-info/licenses/LICENSE
abinator-0.0.6.dist-info/RECORD
