Metadata-Version: 2.1
Name: abinator
Version: 0.0.6
Summary: Python data class-like wrapper for solidity abi specification
Project-URL: Homepage, https://github.com/Whynot63/abinator/
Project-URL: Bug Tracker, https://github.com/Whynot63/abinator/issues
Author-email: Dmitry Andreev <deal.d@me.com>
License: MIT License
License-File: LICENSE
Classifier: Programming Language :: Python :: 3
Requires-Python: >=3.9
